{
  "gif": "001-file_3530.gif",
  "set": "113-貓貓蟲咖波-超讚小萌怪-p_kgiFd0Qhr99HvqruMSAA_by_SigStick3Bot",
  "emotion": "开心满足",
  "action": "开心地竖起大拇指然后翻身摇尾巴",
  "scene": "无背景透明贴纸",
  "description": "蓝色猫猫虫咖波（Capoo）的可爱动画贴纸。咖波身体为圆润的浅蓝色，胸前有白色斑块，粗深灰色轮廓线。动画中咖波先是开心地抬起一只爪子做出竖大拇指的赞好手势，头顶上方有三颗黄色闪光星表示兴奋，双眼眯成弯弯的笑眼，脸颊有红晕线。随后咖波翻身仰躺，尾巴竖起并兴奋地摇晃，尾巴上方有黄色动态线条表示摇摆动作，底部有波浪线表示身体的扭动。最后咖波趴下休息，一只前爪蜷在脸旁，闭着眼睛露出满足安详的微笑。整个动画展示了咖波从开心赞好到翻身玩耍再到安静休息的可爱过程。",
  "tags": ["咖波", "Capoo", "猫猫虫", "竖大拇指", "摇尾巴", "开心", "满足", "翻身", "休息", "可爱", "闪光", "萌"]
}
