{
  "gif": "007-file_5448.gif",
  "set": "185-Bugcat-1-p_6p7QZ27dk8Y5tlrjdfjX_by_SigStick16Bot",
  "emotion": "温馨甜蜜",
  "action": "拥抱依偎",
  "scene": "两个角色亲密依偎在一起",
  "description": "蓝色咖波戴着红白条纹圣诞帽，从身后温柔地依偎着白色圆润角色（小梅），两人紧紧贴在一起。咖波闭眼微笑，露出满足的表情；小梅也闭着眼睛，脸颊上有粉色三线腮红，嘴角微翘露出幸福的微笑。两者之间上方漂浮着一颗粉红色小爱心，营造出甜蜜温馨的氛围。整个动画为循环播放，爱心微微脉动闪烁，角色间有轻微的依偎晃动。",
  "tags": ["咖波", "Bugcat", "Capoo", "拥抱", "依偎", "圣诞帽", "爱心", "温馨", "甜蜜", "亲密", "友情", "小梅", "hug", "cuddle", "love", "santa hat", "heart", "cute", "kawaii", "affectionate"]
}
